marius_project/__init__.py
marius_project/marius.py
Marius_first_project-0.1.2.dist-info/METADATA
Marius_first_project-0.1.2.dist-info/WHEEL
Marius_first_project-0.1.2.dist-info/top_level.txt
Marius_first_project-0.1.2.dist-info/RECORD
