Metadata-Version: 2.1
Name: Marius-first-project
Version: 0.1.2
Summary: First project
Home-page: UNKNOWN
Author: Manea-Marius-Gabriel
Author-email: manea_marius.gabriel@outlook.com
License: UNKNOWN
Platform: UNKNOWN
